doberman/__init__.py
doberman/main.py
doberman-0.0.4.dist-info/LICENSE
doberman-0.0.4.dist-info/METADATA
doberman-0.0.4.dist-info/WHEEL
doberman-0.0.4.dist-info/top_level.txt
doberman-0.0.4.dist-info/RECORD
