Metadata-Version: 2.1
Name: doberman
Version: 0.0.4
Summary: A watchdog that when launched synchronise the remote directory with the content of the local one
Home-page: https://github.com/riccardobernardi/doberman
Author: Bernardi Riccardo
Author-email: riccardo.bernardi@rocketmail.com
License: UNKNOWN
Platform: UNKNOWN
Classifier: Programming Language :: Python :: 3
Classifier: License :: OSI Approved :: MIT License
Classifier: Operating System :: OS Independent
Requires-Dist: bcrypt (==3.2.0)
Requires-Dist: cffi (==1.14.2)
Requires-Dist: cryptography (==3.0)
Requires-Dist: paramiko (==2.7.1)
Requires-Dist: pathtools (==0.1.2)
Requires-Dist: pycparser (==2.20)
Requires-Dist: PyNaCl (==1.4.0)
Requires-Dist: pysftp (==0.2.9)
Requires-Dist: six (==1.15.0)
Requires-Dist: watchdog (==0.10.3)
